image_preprocessor/__init__.py
image_preprocessor-0.1.0.dist-info/LICENSE
image_preprocessor-0.1.0.dist-info/METADATA
image_preprocessor-0.1.0.dist-info/WHEEL
image_preprocessor-0.1.0.dist-info/top_level.txt
image_preprocessor-0.1.0.dist-info/RECORD
