Metadata-Version: 2.1
Name: image-preprocessor
Version: 0.1.0
Summary: Image preprocessor for convolutional neural networks
Home-page: UNKNOWN
Author: Ovikx
License: UNKNOWN
Project-URL: Source code, https://github.com/Ovikx/cnn-image-preprocessor
Platform: UNKNOWN
Classifier: Programming Language :: Python :: 3
Classifier: License :: OSI Approved :: MIT License
Classifier: Operating System :: OS Independent
Requires-Python: >=3.7
License-File: LICENSE
Requires-Dist: Pillow
Requires-Dist: numpy
